bio2bel/__init__.py
bio2bel/__main__.py
bio2bel/automate.py
bio2bel/cli.py
bio2bel/constants.py
bio2bel/downloading.py
bio2bel/exc.py
bio2bel/exthook.py
bio2bel/models.py
bio2bel/obo.py
bio2bel/testing.py
bio2bel/utils.py
bio2bel/version.py
bio2bel/compath/__init__.py
bio2bel/compath/exc.py
bio2bel/compath/manager.py
bio2bel/compath/mixins.py
bio2bel/compath/utils.py
bio2bel/io/__init__.py
bio2bel/io/automate.py
bio2bel/io/pykeen.py
bio2bel/manager/__init__.py
bio2bel/manager/abstract_manager.py
bio2bel/manager/bel_manager.py
bio2bel/manager/cli_manager.py
bio2bel/manager/compath.py
bio2bel/manager/connection_manager.py
bio2bel/manager/flask_manager.py
bio2bel/manager/models.py
bio2bel/manager/namespace_manager.py
bio2bel/sources/__init__.py
bio2bel/sources/biogrid.py
bio2bel/sources/circbase.py
bio2bel/sources/circrnadisease.py
bio2bel/sources/go.py
bio2bel/sources/hmdd.py
bio2bel/sources/intact.py
bio2bel/sources/ncri.py
bio2bel/sources/noncorna.py
bio2bel/sources/pid.py
bio2bel/sources/rhea.py
bio2bel/sources/tfregulons.py
bio2bel/web/__init__.py
bio2bel/web/application.py
bio2bel/web/wsgi.py
bio2bel/web/templates/index.html
bio2bel-0.4.2.dist-info/LICENSE
bio2bel-0.4.2.dist-info/METADATA
bio2bel-0.4.2.dist-info/WHEEL
bio2bel-0.4.2.dist-info/entry_points.txt
bio2bel-0.4.2.dist-info/top_level.txt
bio2bel-0.4.2.dist-info/RECORD
