Metadata-Version: 2.1
Name: bio2bel
Version: 0.4.2
Summary: A framework for converting biological data sources to BEL
Home-page: https://github.com/bio2bel/bio2bel
Author: Charles Tapley Hoyt
Author-email: cthoyt@gmail.com
Maintainer: Charles Tapley Hoyt
Maintainer-email: cthoyt@gmail.com
License: MIT
Download-URL: https://github.com/bio2bel/bio2bel/releases
Project-URL: Bug Tracker, https://github.com/bio2bel/bio2bel/issues
Project-URL: Source Code, https://github.com/bio2bel/bio2bel
Project-URL: Documentation, https://bio2bel.readthedocs.io
Keywords: Biological Expression Language,BEL,Domain Specific Language,DSL,Systems Biology,Networks Biology
Platform: UNKNOWN
Classifier: Development Status :: 4 - Beta
Classifier: Environment :: Console
Classifier: Intended Audience :: Developers
Classifier: Intended Audience :: Science/Research
Classifier: License :: OSI Approved :: MIT License
Classifier: Operating System :: OS Independent
Classifier: Programming Language :: Python
Classifier: Programming Language :: Python :: 3.9
Classifier: Programming Language :: Python :: 3.8
Classifier: Programming Language :: Python :: 3.7
Classifier: Programming Language :: Python :: 3 :: Only
Classifier: Topic :: Scientific/Engineering :: Bio-Informatics
Classifier: Topic :: Scientific/Engineering :: Chemistry
Requires-Python: >=3.7
License-File: LICENSE
Requires-Dist: sqlalchemy
Requires-Dist: click
Requires-Dist: numpy
Requires-Dist: pandas
Requires-Dist: tqdm
Requires-Dist: easy-config
Requires-Dist: pybel (>=0.15.0<0.16.0)
Requires-Dist: bel-resources (>=0.0.3)
Requires-Dist: pyobo (>=0.2.2)
Requires-Dist: pystow (>=0.2.1)
Provides-Extra: docs
Requires-Dist: sphinx ; extra == 'docs'
Requires-Dist: sphinx-rtd-theme ; extra == 'docs'
Requires-Dist: sphinx-click ; extra == 'docs'
Requires-Dist: sphinx-autodoc-typehints ; extra == 'docs'
Provides-Extra: web
Requires-Dist: flask ; extra == 'web'
Requires-Dist: flask-admin ; extra == 'web'
Requires-Dist: flask-bootstrap ; extra == 'web'
